odoo/addons/l10n_nl_account_tax_unece/README.rst
odoo/addons/l10n_nl_account_tax_unece/__init__.py
odoo/addons/l10n_nl_account_tax_unece/__manifest__.py
odoo/addons/l10n_nl_account_tax_unece/post_install.py
odoo/addons/l10n_nl_account_tax_unece/data/account_tax_template.xml
odoo/addons/l10n_nl_account_tax_unece/i18n/l10n_nl_account_tax_unece.pot
odoo/addons/l10n_nl_account_tax_unece/i18n/nl.po
odoo/addons/l10n_nl_account_tax_unece/models/__init__.py
odoo/addons/l10n_nl_account_tax_unece/models/res_company.py
odoo/addons/l10n_nl_account_tax_unece/readme/CONTRIBUTORS.rst
odoo/addons/l10n_nl_account_tax_unece/readme/CREDITS.rst
odoo/addons/l10n_nl_account_tax_unece/readme/DESCRIPTION.rst
odoo/addons/l10n_nl_account_tax_unece/readme/HISTORY.rst
odoo/addons/l10n_nl_account_tax_unece/readme/INSTALL.rst
odoo/addons/l10n_nl_account_tax_unece/readme/USAGE.rst
odoo/addons/l10n_nl_account_tax_unece/static/description/icon.png
odoo/addons/l10n_nl_account_tax_unece/static/description/index.html
odoo/addons/l10n_nl_account_tax_unece/tests/__init__.py
odoo/addons/l10n_nl_account_tax_unece/tests/test_nl_account_tax_unece.py
odoo12_addon_l10n_nl_account_tax_unece-12.0.1.0.0.99.dev4.dist-info/METADATA
odoo12_addon_l10n_nl_account_tax_unece-12.0.1.0.0.99.dev4.dist-info/WHEEL
odoo12_addon_l10n_nl_account_tax_unece-12.0.1.0.0.99.dev4.dist-info/top_level.txt
odoo12_addon_l10n_nl_account_tax_unece-12.0.1.0.0.99.dev4.dist-info/RECORD
